{"moves":[{"moveNumber":1,"color":"white","san":"e4","from":"e2","to":"e4","evalBefore":35,"evalAfter":27,"cploss":8,"accuracy":97,"classification":"good","phase":"opening","tactic":null,"bestMove":"d2d4"},{"moveNumber":1,"color":"black","san":"e5","from":"e7","to":"e5","evalBefore":27,"evalAfter":27,"cploss":0,"accuracy":100,"classification":"good","phase":"opening","tactic":null,"bestMove":"e7e5"},{"moveNumber":2,"color":"white","san":"Nf3","from":"g1","to":"f3","evalBefore":27,"evalAfter":27,"cploss":0,"accuracy":100,"classification":"good","phase":"opening","tactic":null,"bestMove":"g1f3"},{"moveNumber":2,"color":"black","san":"d6","from":"d7","to":"d6","evalBefore":27,"evalAfter":74,"cploss":47,"accuracy":82,"classification":"good","phase":"opening","tactic":null,"bestMove":"b8c6"},{"moveNumber":3,"color":"white","san":"Nc3","from":"b1","to":"c3","evalBefore":74,"evalAfter":37,"cploss":37,"accuracy":86,"classification":"good","phase":"opening","tactic":null,"bestMove":"d2d4"},{"moveNumber":3,"color":"black","san":"h6","from":"h7","to":"h6","evalBefore":37,"evalAfter":66,"cploss":29,"accuracy":89,"classification":"good","phase":"opening","tactic":null,"bestMove":"c7c5"},{"moveNumber":4,"color":"white","san":"g3","from":"g2","to":"g3","evalBefore":66,"evalAfter":22,"cploss":44,"accuracy":83,"classification":"good","phase":"opening","tactic":null,"bestMove":"d2d4"},{"moveNumber":4,"color":"black","san":"Nf6","from":"g8","to":"f6","evalBefore":22,"evalAfter":43,"cploss":21,"accuracy":92,"classification":"good","phase":"opening","tactic":null,"bestMove":"c7c5"},{"moveNumber":5,"color":"white","san":"Bg2","from":"f1","to":"g2","evalBefore":43,"evalAfter":19,"cploss":24,"accuracy":91,"classification":"good","phase":"opening","tactic":null,"bestMove":"d2d4"},{"moveNumber":5,"color":"black","san":"Nxe4","from":"f6","to":"e4","evalBefore":19,"evalAfter":290,"cploss":271,"accuracy":35,"classification":"mistake","phase":"opening","tactic":null,"bestMove":"c7c5"},{"moveNumber":6,"color":"white","san":"Nxe4","from":"c3","to":"e4","evalBefore":290,"evalAfter":294,"cploss":0,"accuracy":100,"classification":"good","phase":"opening","tactic":{"type":"capture","found":true},"bestMove":"c3e4"},{"moveNumber":6,"color":"black","san":"Bg4","from":"c8","to":"g4","evalBefore":294,"evalAfter":316,"cploss":22,"accuracy":93,"classification":"good","phase":"opening","tactic":null,"bestMove":"d6d5"},{"moveNumber":7,"color":"white","san":"O-O","from":"e1","to":"g1","evalBefore":316,"evalAfter":303,"cploss":13,"accuracy":96,"classification":"good","phase":"opening","tactic":null,"bestMove":"e4c3"},{"moveNumber":7,"color":"black","san":"Nc6","from":"b8","to":"c6","evalBefore":303,"evalAfter":316,"cploss":13,"accuracy":96,"classification":"good","phase":"opening","tactic":null,"bestMove":"f7f5"},{"moveNumber":8,"color":"white","san":"h3","from":"h2","to":"h3","evalBefore":316,"evalAfter":330,"cploss":0,"accuracy":100,"classification":"good","phase":"opening","tactic":null,"bestMove":"h2h3"},{"moveNumber":8,"color":"black","san":"Bxf3","from":"g4","to":"f3","evalBefore":330,"evalAfter":406,"cploss":76,"accuracy":81,"classification":"inaccuracy","phase":"opening","tactic":null,"bestMove":"g4e6"},{"moveNumber":9,"color":"white","san":"Qxf3","from":"d1","to":"f3","evalBefore":406,"evalAfter":398,"cploss":8,"accuracy":98,"classification":"good","phase":"opening","tactic":{"type":"sacrifice","found":true},"bestMove":"d1f3"},{"moveNumber":9,"color":"black","san":"Nd4","from":"c6","to":"d4","evalBefore":398,"evalAfter":389,"cploss":0,"accuracy":100,"classification":"good","phase":"opening","tactic":{"type":"fork","found":true},"bestMove":"c6d4"},{"moveNumber":10,"color":"white","san":"Qd3","from":"f3","to":"d3","evalBefore":389,"evalAfter":363,"cploss":26,"accuracy":93,"classification":"good","phase":"opening","tactic":null,"bestMove":"f3d1"},{"moveNumber":10,"color":"black","san":"Be7","from":"f8","to":"e7","evalBefore":363,"evalAfter":394,"cploss":31,"accuracy":92,"classification":"good","phase":"opening","tactic":null,"bestMove":"c7c6"},{"moveNumber":11,"color":"white","san":"c3","from":"c2","to":"c3","evalBefore":394,"evalAfter":326,"cploss":68,"accuracy":83,"classification":"inaccuracy","phase":"middlegame","tactic":null,"bestMove":"e4c3"},{"moveNumber":11,"color":"black","san":"Nc6","from":"d4","to":"c6","evalBefore":326,"evalAfter":445,"cploss":119,"accuracy":73,"classification":"mistake","phase":"middlegame","tactic":null,"bestMove":"d4e6"},{"moveNumber":12,"color":"white","san":"a3","from":"a2","to":"a3","evalBefore":445,"evalAfter":298,"cploss":147,"accuracy":67,"classification":"mistake","phase":"middlegame","tactic":{"type":"fork","found":false},"bestMove":"d3b5"},{"moveNumber":12,"color":"black","san":"d5","from":"d6","to":"d5","evalBefore":298,"evalAfter":321,"cploss":23,"accuracy":93,"classification":"good","phase":"middlegame","tactic":null,"bestMove":"f7f5"},{"moveNumber":13,"color":"white","san":"b4","from":"b2","to":"b4","evalBefore":321,"evalAfter":109,"cploss":212,"accuracy":47,"classification":"mistake","phase":"middlegame","tactic":{"type":"fork","found":false},"bestMove":"d3b5"},{"moveNumber":13,"color":"black","san":"dxe4","from":"d5","to":"e4","evalBefore":109,"evalAfter":120,"cploss":11,"accuracy":96,"classification":"good","phase":"middlegame","tactic":{"type":"capture","found":true},"bestMove":"d5e4"},{"moveNumber":14,"color":"white","san":"Bxe4","from":"g2","to":"e4","evalBefore":120,"evalAfter":68,"cploss":52,"accuracy":81,"classification":"inaccuracy","phase":"middlegame","tactic":null,"bestMove":"d3e4"},{"moveNumber":14,"color":"black","san":"Qxd3","from":"d8","to":"d3","evalBefore":68,"evalAfter":71,"cploss":3,"accuracy":99,"classification":"good","phase":"middlegame","tactic":{"type":"fork","found":true},"bestMove":"d8d3"},{"moveNumber":15,"color":"white","san":"Bxd3","from":"e4","to":"d3","evalBefore":71,"evalAfter":57,"cploss":14,"accuracy":94,"classification":"good","phase":"middlegame","tactic":{"type":"capture","found":true},"bestMove":"e4d3"},{"moveNumber":15,"color":"black","san":"O-O","from":"e8","to":"g8","evalBefore":57,"evalAfter":67,"cploss":10,"accuracy":96,"classification":"good","phase":"middlegame","tactic":null,"bestMove":"e8c8"},{"moveNumber":16,"color":"white","san":"c4","from":"c3","to":"c4","evalBefore":67,"evalAfter":-31,"cploss":98,"accuracy":67,"classification":"inaccuracy","phase":"middlegame","tactic":null,"bestMove":"f1e1"},{"moveNumber":16,"color":"black","san":"Nd4","from":"c6","to":"d4","evalBefore":-31,"evalAfter":-17,"cploss":14,"accuracy":94,"classification":"good","phase":"middlegame","tactic":null,"bestMove":"a7a5"},{"moveNumber":17,"color":"white","san":"Bb2","from":"c1","to":"b2","evalBefore":-17,"evalAfter":-72,"cploss":55,"accuracy":80,"classification":"inaccuracy","phase":"middlegame","tactic":null,"bestMove":"d3e4"},{"moveNumber":17,"color":"black","san":"Nb3","from":"d4","to":"b3","evalBefore":-72,"evalAfter":-38,"cploss":34,"accuracy":87,"classification":"good","phase":"middlegame","tactic":null,"bestMove":"a8d8"},{"moveNumber":18,"color":"white","san":"Rad1","from":"a1","to":"d1","evalBefore":-38,"evalAfter":-48,"cploss":10,"accuracy":96,"classification":"good","phase":"middlegame","tactic":null,"bestMove":"a1d1"},{"moveNumber":18,"color":"black","san":"Bg5","from":"e7","to":"g5","evalBefore":-48,"evalAfter":140,"cploss":188,"accuracy":46,"classification":"mistake","phase":"middlegame","tactic":null,"bestMove":"a8d8"},{"moveNumber":19,"color":"white","san":"Bc3","from":"b2","to":"c3","evalBefore":140,"evalAfter":-18,"cploss":158,"accuracy":52,"classification":"mistake","phase":"middlegame","tactic":{"type":"fork","found":false},"bestMove":"f2f4"},{"moveNumber":19,"color":"black","san":"Rfe8","from":"f8","to":"e8","evalBefore":-18,"evalAfter":62,"cploss":80,"accuracy":72,"classification":"inaccuracy","phase":"middlegame","tactic":null,"bestMove":"a8d8"},{"moveNumber":20,"color":"white","san":"c5","from":"c4","to":"c5","evalBefore":62,"evalAfter":-22,"cploss":84,"accuracy":71,"classification":"inaccuracy","phase":"middlegame","tactic":null,"bestMove":"d3e4"},{"moveNumber":20,"color":"black","san":"e4","from":"e5","to":"e4","evalBefore":-22,"evalAfter":416,"cploss":438,"accuracy":20,"classification":"blunder","phase":"middlegame","tactic":null,"bestMove":"a8d8"},{"moveNumber":21,"color":"white","san":"Bc4","from":"d3","to":"c4","evalBefore":416,"evalAfter":410,"cploss":6,"accuracy":99,"classification":"good","phase":"middlegame","tactic":{"type":"fork","found":true},"bestMove":"d3c4"},{"moveNumber":21,"color":"black","san":"Kh8","from":"g8","to":"h8","evalBefore":410,"evalAfter":501,"cploss":91,"accuracy":82,"classification":"inaccuracy","phase":"middlegame","tactic":null,"bestMove":"b3c5"},{"moveNumber":22,"color":"white","san":"Bxb3","from":"c4","to":"b3","evalBefore":501,"evalAfter":496,"cploss":5,"accuracy":99,"classification":"good","phase":"middlegame","tactic":{"type":"capture","found":true},"bestMove":"c4b3"},{"moveNumber":22,"color":"black","san":"e3","from":"e4","to":"e3","evalBefore":496,"evalAfter":619,"cploss":123,"accuracy":81,"classification":"mistake","phase":"middlegame","tactic":null,"bestMove":"f7f5"},{"moveNumber":23,"color":"white","san":"dxe3","from":"d2","to":"e3","evalBefore":619,"evalAfter":597,"cploss":22,"accuracy":97,"classification":"good","phase":"middlegame","tactic":{"type":"capture","found":true},"bestMove":"d2e3"},{"moveNumber":23,"color":"black","san":"b6","from":"b7","to":"b6","evalBefore":597,"evalAfter":620,"cploss":23,"accuracy":97,"classification":"good","phase":"middlegame","tactic":null,"bestMove":"e8e7"},{"moveNumber":24,"color":"white","san":"Bxf7","from":"b3","to":"f7","evalBefore":620,"evalAfter":652,"cploss":0,"accuracy":100,"classification":"good","phase":"middlegame","tactic":null,"bestMove":"h3h4"},{"moveNumber":24,"color":"black","san":"Rf8","from":"e8","to":"f8","evalBefore":652,"evalAfter":677,"cploss":25,"accuracy":97,"classification":"good","phase":"middlegame","tactic":null,"bestMove":"e8d8"},{"moveNumber":25,"color":"white","san":"Rd7","from":"d1","to":"d7","evalBefore":677,"evalAfter":714,"cploss":0,"accuracy":100,"classification":"good","phase":"middlegame","tactic":null,"bestMove":"d1d7"},{"moveNumber":25,"color":"black","san":"bxc5","from":"b6","to":"c5","evalBefore":714,"evalAfter":759,"cploss":45,"accuracy":96,"classification":"good","phase":"middlegame","tactic":null,"bestMove":"a8d8"},{"moveNumber":26,"color":"white","san":"bxc5","from":"b4","to":"c5","evalBefore":759,"evalAfter":676,"cploss":83,"accuracy":92,"classification":"inaccuracy","phase":"middlegame","tactic":null,"bestMove":"f7d5"},{"moveNumber":26,"color":"black","san":"Rfb8","from":"f8","to":"b8","evalBefore":676,"evalAfter":863,"cploss":187,"accuracy":85,"classification":"mistake","phase":"middlegame","tactic":null,"bestMove":"c7c6"},{"moveNumber":27,"color":"white","san":"Ba2","from":"f7","to":"a2","evalBefore":863,"evalAfter":765,"cploss":98,"accuracy":93,"classification":"inaccuracy","phase":"middlegame","tactic":null,"bestMove":"f7d5"},{"moveNumber":27,"color":"black","san":"Rb5","from":"b8","to":"b5","evalBefore":765,"evalAfter":10000,"cploss":9235,"accuracy":78,"classification":"blunder","phase":"middlegame","tactic":null,"bestMove":"g5f6"},{"moveNumber":28,"color":"white","san":"Bxg7+","from":"c3","to":"g7","evalBefore":10000,"evalAfter":10000,"cploss":0,"accuracy":100,"classification":"good","phase":"middlegame","tactic":{"type":"check","found":true},"bestMove":"c3g7"},{"moveNumber":28,"color":"black","san":"Kh7","from":"h8","to":"h7","evalBefore":10000,"evalAfter":10000,"cploss":0,"accuracy":100,"classification":"good","phase":"middlegame","tactic":null,"bestMove":"h8h7"}],"whiteAccuracy":88,"blackAccuracy":84,"phaseAccuracy":{"white":{"opening":94,"middlegame":84,"endgame":null},"black":{"opening":86,"middlegame":83,"endgame":null}},"tacticAccuracy":{"white":{"found":7,"missed":3,"byType":{"capture":{"found":4,"missed":0},"sacrifice":{"found":1,"missed":0},"fork":{"found":1,"missed":3},"check":{"found":1,"missed":0}}},"black":{"found":3,"missed":0,"byType":{"fork":{"found":2,"missed":0},"capture":{"found":1,"missed":0}}}},"summary":{"blunders":{"white":0,"black":2},"mistakes":{"white":3,"black":5},"inaccuracies":{"white":7,"black":3}}}